pix2tex/__init__.py
pix2tex/__main__.py
pix2tex/cli.py
pix2tex/eval.py
pix2tex/gui.py
pix2tex/models.py
pix2tex/setup_desktop.py
pix2tex/train.py
pix2tex/train_resizer.py
pix2tex/api/__init__.py
pix2tex/api/app.py
pix2tex/api/run.py
pix2tex/api/streamlit.py
pix2tex/dataset/__init__.py
pix2tex/dataset/arxiv.py
pix2tex/dataset/dataset.py
pix2tex/dataset/demacro-test.py
pix2tex/dataset/demacro.py
pix2tex/dataset/extract_latex.py
pix2tex/dataset/latex2png.py
pix2tex/dataset/postprocess.py
pix2tex/dataset/render.py
pix2tex/dataset/scraping.py
pix2tex/dataset/transforms.py
pix2tex/dataset/preprocessing/__init__.py
pix2tex/dataset/preprocessing/generate_latex_vocab.py
pix2tex/dataset/preprocessing/preprocess_formulas.py
pix2tex/model/__init__.py
pix2tex/model/checkpoints/__init__.py
pix2tex/model/checkpoints/get_latest_checkpoint.py
pix2tex/model/dataset/tokenizer.json
pix2tex/model/settings/config-vit.yaml
pix2tex/model/settings/config.yaml
pix2tex/model/settings/debug.yaml
pix2tex/models/__init__.py
pix2tex/models/hybrid.py
pix2tex/models/transformer.py
pix2tex/models/utils.py
pix2tex/models/vit.py
pix2tex/resources/MathJax.js
pix2tex/resources/__init__.py
pix2tex/resources/icon.svg
pix2tex/resources/processing-icon-anim.svg
pix2tex/resources/resources.py
pix2tex/resources/resources.qrc
pix2tex/utils/__init__.py
pix2tex/utils/utils.py
pix2tex-0.1.4.dist-info/LICENSE
pix2tex-0.1.4.dist-info/METADATA
pix2tex-0.1.4.dist-info/WHEEL
pix2tex-0.1.4.dist-info/entry_points.txt
pix2tex-0.1.4.dist-info/top_level.txt
pix2tex-0.1.4.dist-info/RECORD
