Metadata-Version: 2.1
Name: pix2tex
Version: 0.1.4
Summary: pix2tex: Using a ViT to convert images of equations into LaTeX code.
Home-page: https://github.com/lukas-blecher/LaTeX-OCR/
Author: Lukas Blecher
Author-email: luk.blecher@gmail.com
License: MIT
Keywords: artificial intelligence,deep learning,image to text
Platform: UNKNOWN
Classifier: Development Status :: 4 - Beta
Classifier: Intended Audience :: Science/Research
Classifier: Topic :: Scientific/Engineering :: Artificial Intelligence
Classifier: License :: OSI Approved :: MIT License
Classifier: Programming Language :: Python
License-File: LICENSE
Requires-Dist: tqdm (>=4.47.0)
Requires-Dist: munch (>=2.5.0)
Requires-Dist: torch (>=1.7.1)
Requires-Dist: opencv-python-headless (>=4.1.1.26)
Requires-Dist: requests (>=2.22.0)
Requires-Dist: einops (>=0.3.0)
Requires-Dist: x-transformers (==0.15.0)
Requires-Dist: transformers (>=4.18.0)
Requires-Dist: tokenizers (>=0.13.0)
Requires-Dist: numpy (>=1.19.5)
Requires-Dist: Pillow (>=9.1.0)
Requires-Dist: PyYAML (>=5.4.1)
Requires-Dist: pandas (>=1.0.0)
Requires-Dist: timm (==0.5.4)
Requires-Dist: albumentations (<=1.4.24,>=0.5.2)
Requires-Dist: pyreadline3 (>=3.4.1) ; platform_system == "Windows"
Provides-Extra: all
Requires-Dist: PyQt6 ; extra == 'all'
Requires-Dist: PyQt6-WebEngine ; extra == 'all'
Requires-Dist: pyside6 ; extra == 'all'
Requires-Dist: pynput ; extra == 'all'
Requires-Dist: screeninfo ; extra == 'all'
Requires-Dist: latex2sympy2 ; extra == 'all'
Requires-Dist: streamlit (>=1.8.1) ; extra == 'all'
Requires-Dist: fastapi (>=0.75.2) ; extra == 'all'
Requires-Dist: uvicorn[standard] ; extra == 'all'
Requires-Dist: python-multipart ; extra == 'all'
Requires-Dist: st-img-pastebutton (>=0.0.3) ; extra == 'all'
Requires-Dist: python-Levenshtein (>=0.12.2) ; extra == 'all'
Requires-Dist: torchtext (>=0.6.0) ; extra == 'all'
Requires-Dist: imagesize (>=1.2.0) ; extra == 'all'
Requires-Dist: pygments ; extra == 'all'
Provides-Extra: api
Requires-Dist: streamlit (>=1.8.1) ; extra == 'api'
Requires-Dist: fastapi (>=0.75.2) ; extra == 'api'
Requires-Dist: uvicorn[standard] ; extra == 'api'
Requires-Dist: python-multipart ; extra == 'api'
Requires-Dist: st-img-pastebutton (>=0.0.3) ; extra == 'api'
Provides-Extra: gui
Requires-Dist: PyQt6 ; extra == 'gui'
Requires-Dist: PyQt6-WebEngine ; extra == 'gui'
Requires-Dist: pyside6 ; extra == 'gui'
Requires-Dist: pynput ; extra == 'gui'
Requires-Dist: screeninfo ; extra == 'gui'
Requires-Dist: latex2sympy2 ; extra == 'gui'
Provides-Extra: highlight
Requires-Dist: pygments ; extra == 'highlight'
Provides-Extra: train
Requires-Dist: python-Levenshtein (>=0.12.2) ; extra == 'train'
Requires-Dist: torchtext (>=0.6.0) ; extra == 'train'
Requires-Dist: imagesize (>=1.2.0) ; extra == 'train'
